oxfs/__init__.py
oxfs/lock.py
oxfs/oxfs.py
oxfs/updater.py
oxfs/cache/__init__.py
oxfs/cache/fs.py
oxfs/cache/meta.py
oxfs-0.5.5.dist-info/LICENSE
oxfs-0.5.5.dist-info/METADATA
oxfs-0.5.5.dist-info/WHEEL
oxfs-0.5.5.dist-info/entry_points.txt
oxfs-0.5.5.dist-info/top_level.txt
oxfs-0.5.5.dist-info/zip-safe
oxfs-0.5.5.dist-info/RECORD
