Metadata-Version: 2.1
Name: oxfs
Version: 0.5.5
Summary: A Fast SFTP File System
Home-page: https://github.com/oxfs/oxfs
Author: RainMark
Author-email: rain.by.zhou@gmail.com
Classifier: Operating System :: Unix
Classifier: Operating System :: MacOS
Classifier: Operating System :: POSIX :: Linux
Classifier: Programming Language :: Python :: 3 :: Only
Classifier: License :: OSI Approved :: MIT License
License-File: LICENSE
Requires-Dist: fusepy (==3.0.1)
Requires-Dist: paramiko (>=2.0.0)
Requires-Dist: xxhash (>=1.3.0)
